Metadata-Version: 1.1
Name: vigimeteo
Version: 0.0.1b1.dev1
Summary: Current French West Indies weather awareness level (Vigilance Meteo)
Home-page: https://github.com/Alert-Box/vigimeteo
Author: Olivier Watte
Author-email: owatte@emnet.cc
License: UNKNOWN
Platform: UNKNOWN
Classifier: Programming Language :: Python
Classifier: Development Status :: 2 - Pre-Alpha
Classifier: Environment :: Console
Classifier: Intended Audience :: End Users/Desktop
Classifier: License :: OSI Approved :: GNU Lesser General Public License v3 or later (LGPLv3+)
Classifier: Natural Language :: French
Classifier: Operating System :: OS Independent
Classifier: Programming Language :: Python :: 2.7
Classifier: Topic :: Utilities
